{
  "sections": {
    "page": {
      "type": "page",
      "disabled": true,
      "settings": {
        "color_scheme": "default",
        "container_size": "large",
        "section_spacing_top": 96,
        "section_spacing_bottom": 96,
        "show_heading": true
      }
    },
    "adeedd80-03c5-4edb-870f-21dd4e983233": {
      "type": "ingredients-breadcrumbs",
      "disabled": true,
      "settings": {
      }
    },
    "fae1b60a-608f-44ac-99b4-d1deb62e1a64": {
      "type": "ingredients-hero-banner",
      "settings": {
        "text_color": "#ffffff",
        "desktop_section_height": 260,
        "mobile_section_height": 260,
        "show_collection_image": true,
        "show_page_title": true,
        "desktop_overlay_opacity": 10,
        "mobile_overlay_opacity": 0,
        "desktop_content_position": "align-items:center;justify-content:center;",
        "desktop_content_align": "center",
        "content_max_width": 1304,
        "content_spacing": 48,
        "mobile_content_position": "align-items:center;",
        "mobile_content_align": "center"
      }
    },
    "ac1a7540-47a6-4f4e-bdc9-973e3feaeab3": {
      "type": "ingredients-description",
      "settings": {
        "section_max_width": 900,
        "container_size": "small",
        "description_title": "About",
        "description_title_font_size": 24,
        "description_title_font_size_for_mobile": 20,
        "description_content_font_size": 20,
        "description_content_font_size_for_mobile": 16,
        "description_text_align": "left_aligned"
      }
    },
    "ab3f7364-5240-43f7-b368-f03af192e588": {
      "type": "ingredients-benefits",
      "settings": {
        "benefit_title": "Benefits"
      }
    },
    "26e6c122-c3e8-4690-8f51-067c95684876": {
      "type": "featured-collection",
      "settings": {
        "title": "Found in",
        "shop_all_title": "",
        "shop_all_url": "",
        "collection": "all-products",
        "featured_products": [

        ],
        "enable_autoplay": false,
        "autoplay_interval": 3
      }
    },
    "652db47c-20aa-460d-89ea-50fb5e602c22": {
      "type": "ingredients-article",
      "settings": {
        "container_size": "small",
        "section_title": "THE SCIENCE BEHIND THE BENEFITS",
        "articles_section_title_font_size": 24
      }
    },
    "42323dca-3e20-479f-8a1f-ea4e175f8816": {
      "type": "ingrediants-science-behind-benefit",
      "settings": {
        "section_heading": "THE SCIENCE BEHIND THE BENEFITS"
      }
    }
  },
  "order": [
    "page",
    "adeedd80-03c5-4edb-870f-21dd4e983233",
    "fae1b60a-608f-44ac-99b4-d1deb62e1a64",
    "ac1a7540-47a6-4f4e-bdc9-973e3feaeab3",
    "ab3f7364-5240-43f7-b368-f03af192e588",
    "26e6c122-c3e8-4690-8f51-067c95684876",
    "652db47c-20aa-460d-89ea-50fb5e602c22",
    "42323dca-3e20-479f-8a1f-ea4e175f8816"
  ]
}